{
  "routerMap": [
    {
      "name": "web_login",
      "pageSourceFile": "src/main/ets/view/login/WebLogin.ets",
      "buildFunction": "WebLoginPage"
    },
    {
      "name": "register",
      "pageSourceFile": "src/main/ets/view/login/RegisterPage.ets",
      "buildFunction": "RegisterPage"
    },
    {
      "name": "token_login",
      "pageSourceFile": "src/main/ets/view/login/TokenLogin.ets",
      "buildFunction": "TokenLoginPage"
    },
    {
      "name": "illust_detail",
      "pageSourceFile": "src/main/ets/view/IllustDetailPage.ets",
      "buildFunction": "IllustDetailBuilder"
    },
    {
      "name": "user_detail",
      "pageSourceFile": "src/main/ets/view/user/UserDetailPage.ets",
      "buildFunction": "UserDetailBuilder"
    },
    {
      "name": "search_page",
      "pageSourceFile": "src/main/ets/pages/Search.ets",
      "buildFunction": "SearchContentBuilder"
    },
    {
      "name": "searching_page",
      "pageSourceFile": "src/main/ets/view/SearchingPage.ets",
      "buildFunction": "SearchingPageBuilder"
    },
    {
      "name": "download_manager",
      "pageSourceFile": "src/main/ets/view/more/DownloadManager.ets",
      "buildFunction": "DownloadManagerBuilder"
    },
    {
      "name": "user_accounts",
      "pageSourceFile": "src/main/ets/view/user/UserAccounts.ets",
      "buildFunction": "UserAccountsBuilder"
    },
    {
      "name": "login",
      "pageSourceFile": "src/main/ets/pages/Login.ets",
      "buildFunction": "LoginBuilder"
    }
  ]
}